anywidget_ipyniivue/__init__.py
anywidget_ipyniivue/static/widget.css
anywidget_ipyniivue/static/widget.js
anywidget_ipyniivue-0.0.1.dist-info/METADATA
anywidget_ipyniivue-0.0.1.dist-info/WHEEL
anywidget_ipyniivue-0.0.1.dist-info/RECORD
